{
  "2005 Player Cards": "1391",
  "2006 Player Cards": "1269",
  "2007 Player Cards": "1392",
  "Aaron Miller Tokens": "2517",
  "Adventures in the Forgotten Realms": "4259",
  "Adventures in the Forgotten Realms Extras": "4260",
  "Adventures in the Forgotten Realms Promos": "4358",
  "Aether Revolt": "1718",
  "Aether Revolt Promos": "1750",
  "Alara Block All-Foil Booster": "1592",
  "Alara Reborn": "108",
  "Alliances": "15",
  "Alpha": "1",
  "ALRadeck Tokens": "2520",
  "Amaranth Alchemy Tokens": "3043",
  "Amonkhet": "1729",
  "Amonkhet Invocations": "1798",
  "Amonkhet Promos": "1803",
  "Andrew Thompson Tokens": "3349",
  "Angelarium Tokens": "2523",
  "Anthologies": "75",
  "Anthony Christou Tokens": "3344",
  "Antiquities": "5",
  "APAC Lands": "97",
  "Apocalypse": "36",
  "Arabian Nights": "4",
  "Archenemy": "1194",
  "Archenemy Nicol Bolas": "1730",
  "Arena League Promos": "89",
  "Armada Comics": "117",
  "Artists of Magic": "1429",
  "Avacyn Restored": "1358",
  "Battle for Zendikar": "1668",
  "Battle for Zendikar Promos": "1670",
  "Battle Royale": "64",
  "Battlebond": "2111",
  "Battlebond Promos": "2333",
  "Beatdown": "62",
  "Beta": "2",
  "Betrayers of Kamigawa": "51",
  "BoM Products": "1697",
  "Born of the Gods": "1469",
  "Buy a Box Promos": "1198",
  "Card Game Tokens": "2956",
  "Cardamajigs Tokens": "2526",
  "Cardmarket Tokens": "1662",
  "CardZ Promos": "1342",
  "Cats & Cantrips Tokens": "2529",
  "Champions of Kamigawa": "48",
  "Champs & States Promos": "94",
  "Chronicles": "12",
  "Chronicles Japanese": "1599",
  "Clash Pack Promos": "1490",
  "Classic Art Tokens": "2572",
  "Coldsnap": "52",
  "Coldsnap Theme Decks": "82",
  "Collectors' Edition": "61",
  "Commander": "1273",
  "Commander 2013": "1464",
  "Commander 2014": "1513",
  "Commander 2015": "1679",
  "Commander 2016": "1719",
  "Commander 2017": "1813",
  "Commander 2018": "2110",
  "Commander 2019": "2448",
  "Commander Anthology": "1732",
  "Commander Anthology II": "2109",
  "Commander Collection Green": "3394",
  "Commander Legends": "3454",
  "Commander Legends Extras": "3459",
  "Commander Adventures in the Forgotten Realms": "4356",
  "Commander Adventures in the Forgotten Realms Extras": "4359",
  "Commander Ikoria": "2911",
  "Commander Innistrad Crimson Vow": "4366",
  "Commander Innistrad Midnight Hunt": "4365",
  "Commander Kaldheim": "3685",
  "Commander Strixhaven": "3756",
  "Commander Strixhaven Extras": "4175",
  "Commander Zendikar Rising": "3399",
  "Commander's Arsenal": "1418",
  "Conflux": "106",
  "Conspiracy": "1483",
  "Conspiracy Take the Crown": "1702",
  "Convention Promos": "1597",
  "Core 2019": "1835",
  "Core 2019 Promos": "2337",
  "Core 2020": "2447",
  "Core 2020 Extras": "2490",
  "Core 2021": "3048",
  "Core 2021 Extras": "3309",
  "Core 2021 Promos": "3319",
  "Creature Forge Overwhelming Swarm": "2383",
  "Custom Tokens": "1499",
  "Dark Ascension": "1345",
  "Darksteel": "46",
  "DCI Promos": "66",
  "Deckmasters": "67",
  "Dengeki Maoh Promos": "1248",
  "Dissension": "53",
  "Dominaria": "1822",
  "Dominaria Promos": "2315",
  "Double Masters": "3204",
  "Double Masters Extras": "3209",
  "Dragon's Maze": "1435",
  "Dragons of Tarkir": "1601",
  "Dragons Of Tarkir Promos": "1602",
  "Duel Decks Ajani vs Nicol Bolas": "1288",
  "Duel Decks Anthology": "1509",
  "Duel Decks Blessed vs Cursed": "1692",
  "Duel Decks Divine vs Demonic": "107",
  "Duel Decks Elspeth vs Kiora": "1593",
  "Duel Decks Elspeth vs Tezzeret": "1203",
  "Duel Decks Elves vs Goblins": "91",
  "Duel Decks Elves vs Inventors": "2068",
  "Duel Decks Garruk vs Liliana": "115",
  "Duel Decks Heroes vs Monsters": "1456",
  "Duel Decks Izzet vs Golgari": "1398",
  "Duel Decks Jace vs Chandra": "104",
  "Duel Decks Jace vs Vraska": "1477",
  "Duel Decks Knights vs Dragons": "1261",
  "Duel Decks Merfolk vs Goblins": "1818",
  "Duel Decks Mind vs Might": "1728",
  "Duel Decks Nissa vs Ob Nixilis": "1720",
  "Duel Decks Phyrexia vs The Coalition": "119",
  "Duel Decks Sorin vs Tibalt": "1430",
  "Duel Decks Speed vs Cunning": "1496",
  "Duel Decks Venser vs Koth": "1350",
  "Duel Decks Zendikar vs Eldrazi": "1663",
  "Duels of the Planeswalkers Decks": "1193",
  "Duels of the Planeswalkers Promos": "1278",
  "Durdling Around Tokens": "2532",
  "Eighth Edition": "44",
  "Eldritch Moon": "1695",
  "Eldritch Moon Promos": "1723",
  "Eternal Masters": "1696",
  "Euro Lands": "81",
  "Eventide": "99",
  "Exodus": "21",
  "Explorers of Ixalan": "1830",
  "Fallen Empires": "9",
  "Fallen Empires Wyvern Misprints": "1638",
  "Fate Reforged": "1522",
  "Fate Reforged Promos": "1589",
  "Fifth Dawn": "47",
  "Fifth Edition": "23",
  "Filler Cards": "1408",
  "Foreign Black Bordered": "57",
  "Foreign White Bordered": "73",
  "Fourth Edition": "10",
  "Fourth Edition Alternate": "1600",
  "Fourth Edition Black Bordered": "1332",
  "Friday Night Magic Promos": "72",
  "From the Vault Angels": "1661",
  "From the Vault Annihilation": "1494",
  "From the Vault Dragons": "100",
  "From the Vault Exiled": "112",
  "From the Vault Legends": "1286",
  "From the Vault Lore": "1703",
  "From the Vault Realms": "1397",
  "From the Vault Relics": "1202",
  "From the Vault Transform": "1819",
  "From the Vault Twenty": "1455",
  "Future Sight": "70",
  "Game Day Promos": "1209",
  "Game Night 2019": "2804",
  "GamingEtc Tokens": "1642",
  "Gatecrash": "1424",
  "Gateway Promos": "78",
  "Givememana's Tokens": "2552",
  "Global Series Jiang Yanggu & Mu Yanling": "2108",
  "GnD Cards": "1691",
  "Grand Prix Promos": "1595",
  "Guildpact": "54",
  "Guilds of Ravnica": "2348",
  "Guilds of Ravnica Extras": "2371",
  "Guilds of Ravnica Guild Kits": "2379",
  "Guilds of Ravnica Mythic Edition": "2373",
  "Guru Lands": "88",
  "Happy Holidays Promos": "1247",
  "Harper Prism Promos": "71",
  "Hascon 2017 Promos": "1841",
  "Heroes of the Realm Promos": "2417",
  "Hobby Japan Commemorative Promos": "1421",
  "Homelands": "14",
  "Hour of Devastation": "1731",
  "Hour of Devastation Promos": "1825",
  "Human for Scale Tokens": "2557",
  "Ice Age": "11",
  "Iconic Masters": "1811",
  "IDW Promos": "1413",
  "Ikoria Lair of Behemoths": "2819",
  "Ikoria Lair of Behemoths Extras": "3113",
  "Ikoria Lair of Behemoths Promos": "3118",
  "Innistrad": "1327",
  "Innistrad Crimson Vow": "4364",
  "Innistrad Midnight Hunt": "4362",
  "Innistrad Midnight Hunt Extras": "4363",
  "International Edition": "77",
  "Introductory Two-Player Set": "85",
  "Invasion": "34",
  "Ixalan": "1812",
  "Ixalan Promos": "1847",
  "Japan Junior Tournament Promos": "87",
  "Jason Engle Tokens": "2562",
  "Javi Alterations Tokens": "1705",
  "JingHe Age 2002 Tokens": "1328",
  "JingHe Age MtG 10th Anniversary Tokens": "1329",
  "Johannes Voss Tokens": "2114",
  "Journey into Nyx": "1481",
  "Judge Program Tokens": "1643",
  "Judge Rewards Promos": "80",
  "Judgment": "40",
  "Jumpstart": "3053",
  "Junior APAC Series Promos": "1586",
  "Junior Series Promos": "1361",
  "Junior Super Series Promos": "86",
  "Kaladesh": "1717",
  "Kaladesh Inventions": "1733",
  "Kaladesh Promos": "1726",
  "Kaldheim": "3660",
  "Kaldheim Extras": "3680",
  "Kaldheim Promos": "3723",
  "Khans of Tarkir": "1495",
  "Khans of Tarkir Promos": "1588",
  "Kraken Wargames Playmats": "3469",
  "League Promos": "1594",
  "Legends": "7",
  "Legends Italian": "1838",
  "Legions": "42",
  "Limited Edition Alpha": "1",
  "Limited Edition Beta": "2",
  "Lorwyn": "84",
  "Magic 2010": "109",
  "Magic 2011": "1197",
  "Magic 2012": "1280",
  "Magic 2013": "1388",
  "Magic 2014": "1449",
  "Magic 2015": "1485",
  "Magic Game Night": "2381",
  "Magic Origins": "1652",
  "Magic Origins Promos": "1655",
  "Magic Premiere Shop Promos": "101",
  "Magic Scholarship Series Promos": "1360",
  "Magic the Gathering Products": "1407",
  "MagicFest Promos": "2413",
  "Mark Poole Tokens": "2457",
  "Masters 25": "1820",
  "Mercadian Masques": "31",
  "Mezzocielo & Friends Classic Tokens": "1834",
  "Mezzocielo & Friends Mini Tokens": "1765",
  "Mirage": "16",
  "Mirrodin": "45",
  "Mirrodin Besieged": "1253",
  "Misprints": "1367",
  "MKM Series": "1665",
  "Modern Event Deck 2014": "1484",
  "Modern Horizons": "2440",
  "Modern Horizons 2": "4219",
  "Modern Horizons 2 Extras": "4244",
  "Modern Horizons 2 Promos": "4327",
  "Modern Horizons Art Series": "2484",
  "Modern Horizons Retro Frame Cards": "4275",
  "Modern Masters": "1444",
  "Modern Masters 2015": "1641",
  "Modern Masters 2017": "1727",
  "Morningtide": "92",
  "Multiverse Gift Box": "1519",
  "Mystery Booster": "2874",
  "Mystery Booster Playtest Cards": "2869",
  "Mystical Archive": "3746",
  "Nemesis": "32",
  "New Phyrexia": "1262",
  "Ninth Edition": "49",
  "Oath of the Gatewatch": "1676",
  "Oath of the Gatewatch Promos": "1686",
  "Odyssey": "38",
  "Old School Tokens": "2360",
  "Onslaught": "41",
  "Open House Promos": "1844",
  "Oversized 6x9 Promos": "110",
  "Oversized 9x12 Promos": "1639",
  "Oversized Box Toppers": "111",
  "Perfektpro Products": "1654",
  "Planar Chaos": "58",
  "Planechase": "113",
  "Planechase 2012": "1369",
  "Planechase Anthology": "1722",
  "Planeshift": "35",
  "Player Rewards Promos": "79",
  "Ponies The Galloping": "2699",
  "Portal": "25",
  "Portal Second Age": "24",
  "Portal Three Kingdoms": "30",
  "Premium Deck Series Fire & Lightning": "1218",
  "Premium Deck Series Graveborn": "1337",
  "Premium Deck Series Slivers": "116",
  "Prerelease Promos": "83",
  "Pro Tour 1996 Bertrand Lestree": "121",
  "Pro Tour 1996 Collector Set": "1516",
  "Pro Tour 1996 Eric Tam": "122",
  "Pro Tour 1996 George Baxter": "123",
  "Pro Tour 1996 Leon Lindback": "124",
  "Pro Tour 1996 Mark Justice": "125",
  "Pro Tour 1996 Michael Locanto": "126",
  "Pro Tour 1996 Preston Poulter": "127",
  "Pro Tour 1996 Shawn Regnier": "128",
  "Pro Tour Promos": "1596",
  "Promos": "1249",
  "Prophecy": "33",
  "Ravnica Allegiance": "2411",
  "Ravnica Allegiance Extras": "2419",
  "Ravnica Allegiance Guild Kits": "2423",
  "Ravnica Allegiance Mythic Edition": "2422",
  "Ravnica City of Guilds": "55",
  "Release Promos": "1210",
  "Relic Tokens Eternal Collection": "2115",
  "Relic Tokens Legendary Collection": "2433",
  "Relic Tokens Lineage Collection": "2402",
  "Relic Tokens Promos": "2403",
  "Renaissance": "60",
  "Resale Promos": "98",
  "Return to Ravnica": "1389",
  "Revised": "6",
  "Revista Serra Promos": "1432",
  "Rinascimento": "96",
  "Rise of the Eldrazi": "120",
  "Rivals of Ixalan": "1829",
  "Rivals of Ixalan Promos": "2063",
  "Rk post Products": "1833",
  "Salvat-Hachette": "105",
  "Salvat-Hachette 2011": "1259",
  "San Diego Comic-Con 2013 Promos": "1454",
  "San Diego Comic-Con 2014 Promos": "1491",
  "San Diego Comic-Con 2015 Promos": "1658",
  "San Diego Comic-Con 2016 Promos": "1725",
  "San Diego Comic-Con 2017 Promos": "1828",
  "San Diego Comic-Con 2018 Promos": "2341",
  "San Diego Comic-Con 2019 Promos": "2511",
  "Saviors of Kamigawa": "50",
  "Scars of Mirrodin": "1206",
  "Scourge": "43",
  "Secret Lair Drop Series": "2901",
  "Secret Lair Drop Series All-Natural, Totally Refreshing Superdrop": "4335",
  "Secret Lair Drop Series Dr Lair's Secretorium Superdrop": "4334",
  "Secret Lair Ultimate Edition": "3068",
  "Seventh Edition": "37",
  "Shadowmoor": "95",
  "Shadows over Innistrad": "1694",
  "Shadows over Innistrad Promos": "1704",
  "Shards of Alara": "102",
  "Signature Spellbook Chandra": "3063",
  "Signature Spellbook Gideon": "2460",
  "Signature Spellbook Jace": "2103",
  "Simplified Chinese Alternate Art Cards": "1401",
  "Sixth Edition": "29",
  "Standard Series Promos": "1809",
  "Standard Showdown Promos": "1836",
  "Starcity Games Commemorative Tokens": "1500",
  "Starcity Games Creature Collection": "1501",
  "Starcity Games Justin Treadway Tokens": "1438",
  "Starcity Games Kristen Plescow Tokens": "1512",
  "Starcity Games Token Series One": "1514",
  "Starter 1999": "63",
  "Starter 2000": "65",
  "Store Championship Promos": "2023",
  "Strixhaven Mystical Archive": "3746",
  "Strixhaven School of Mages": "3741",
  "Strixhaven School of Mages Extras": "3761",
  "Strixhaven School of Mages Promos": "4176",
  "Stronghold": "20",
  "Summer Magic": "76",
  "Tempest": "19",
  "Tenth Edition": "74",
  "The Dark": "8",
  "The Dark Italian": "1837",
  "The Duelist Promos": "93",
  "The List": "3494",
  "Theros": "1457",
  "Theros Beyond Death": "2814",
  "Theros Beyond Death Extras": "2961",
  "Theros Beyond Death Promos": "2999",
  "Throne of Eldraine": "2582",
  "Throne of Eldraine Extras": "2587",
  "Throne of Eldraine Promos": "2694",
  "Tierra Media Tokens": "1511",
  "Time Spiral": "56",
  "Time Spiral Remastered": "3766",
  "Time Spiral Remastered Extras": "3771",
  "Tokens for MTG": "1502",
  "Tokens of Spirit": "2567",
  "TokyoMTG Products": "1515",
  "TopDeck Promos": "129",
  "Torment": "39",
  "Ugin's Fate Promos": "1587",
  "Ultimate Box Toppers": "2398",
  "Ultimate Masters": "2397",
  "Ultra-Pro Puzzle Cards": "1451",
  "Unglued": "22",
  "Unhinged": "59",
  "Unlimited": "3",
  "Unsanctioned": "2809",
  "Unstable": "1821",
  "Urza's Destiny": "28",
  "Urza's Legacy": "27",
  "Urza's Saga": "26",
  "Vanguard": "69",
  "Visions": "17",
  "War of the Spark": "2439",
  "War of the Spark Extras": "2451",
  "War of the Spark Japanese Alternate-Art Planeswalkers": "2461",
  "War of the Spark Mythic Edition": "2459",
  "WCD 1997 Jakub Slemr": "1199",
  "WCD 1997 Janosch Kuhn": "1200",
  "WCD 1997 Paul McCabe": "1292",
  "WCD 1997 Svend Geertsen": "1293",
  "WCD 1998 Ben Rubin": "1296",
  "WCD 1998 Brian Hacker": "1295",
  "WCD 1998 Brian Selden": "1297",
  "WCD 1998 Randy Buehler": "1294",
  "WCD 1999 Jakub Šlemr": "1298",
  "WCD 1999 Kai Budde": "1301",
  "WCD 1999 Mark Le Pine": "1300",
  "WCD 1999 Matt Linde": "1299",
  "WCD 2000 Janosch Kühn": "1304",
  "WCD 2000 Jon Finkel": "1305",
  "WCD 2000 Nicolas Labarre": "1302",
  "WCD 2000 Tom Van de Logt": "1303",
  "WCD 2001 Alex Borteh": "1308",
  "WCD 2001 Antoine Ruel": "1307",
  "WCD 2001 Jan Tomcani": "1306",
  "WCD 2001 Tom van de Logt": "1309",
  "WCD 2002 Brian Kibler": "1312",
  "WCD 2002 Carlos Romao": "1313",
  "WCD 2002 Raphael Levy": "1311",
  "WCD 2002 Sim Han How": "1310",
  "WCD 2003 Daniel Zink": "1317",
  "WCD 2003 Dave Humpherys": "1316",
  "WCD 2003 Peer Kröger": "1314",
  "WCD 2003 Wolfgang Eder": "1315",
  "WCD 2004 Aeo Paquette": "1320",
  "WCD 2004 Gabriel Nassif": "1318",
  "WCD 2004 Julien Nuijten": "1321",
  "WCD 2004 Manuel Bevand": "1319",
  "Weatherlight": "18",
  "Weekend Promos": "2372",
  "Welcome Deck 2016": "1710",
  "Welcome Deck 2017": "1802",
  "Worldwake": "118",
  "Your Move Games Tokens": "1281",
  "Yummy Tokens": "1659",
  "Zendikar": "114",
  "Zendikar Expeditions": "1669",
  "Zendikar Rising": "3404",
  "Zendikar Rising Expeditions": "3489",
  "Zendikar Rising Extras": "3474",
  "Zendikar Rising Promos": "3500"
}